slimt.libs/libopenblas-r0-f650aae0.3.3.so
slimt.libs/libquadmath-96973f99.so.0.0.0
slimt.libs/libgfortran-91cc3cb1.so.3.0.0
slimt/__main__.py
slimt/__init__.py
slimt/utils.py
slimt/cmds.py
slimt/_slimt.cpython-311-x86_64-linux-gnu.so
slimt/typing_utils.py
slimt/repository.py
slimt/iterators.py
slimt/tests/test_iterators.py
slimt/tests/test_cmdline.py
slimt/tests/test_ende_borked_base.py
slimt/tests/conftest.py
slimt/tests/test_pivot.py
slimt/tests/test_encoding.py
slimt/tests/test_basic.py
slimt-0.1.0.dist-info/WHEEL
slimt-0.1.0.dist-info/top_level.txt
slimt-0.1.0.dist-info/LICENSE
slimt-0.1.0.dist-info/entry_points.txt
slimt-0.1.0.dist-info/RECORD
slimt-0.1.0.dist-info/METADATA
